LICENSE
MANIFEST.in
README.md
setup.py
nonebot_plugin_gakuenImasCalculator/OCRattrs.py
nonebot_plugin_gakuenImasCalculator/__init__.py
nonebot_plugin_gakuenImasCalculator/blue.jpg
nonebot_plugin_gakuenImasCalculator/blue.png
nonebot_plugin_gakuenImasCalculator/blue2.jpg
nonebot_plugin_gakuenImasCalculator/calc.py
nonebot_plugin_gakuenImasCalculator/calcfun.py
nonebot_plugin_gakuenImasCalculator/downloadpic.py
nonebot_plugin_gakuenImasCalculator/red.jpg
nonebot_plugin_gakuenImasCalculator/red.png
nonebot_plugin_gakuenImasCalculator/red2.jpg
nonebot_plugin_gakuenImasCalculator/test.jpg
nonebot_plugin_gakuenImasCalculator/test.py
nonebot_plugin_gakuenImasCalculator/test1.jpg
nonebot_plugin_gakuenImasCalculator/test2.jpg
nonebot_plugin_gakuenImasCalculator/test3.jpg
nonebot_plugin_gakuenImasCalculator/test4.jpg
nonebot_plugin_gakuenImasCalculator/test4.png
nonebot_plugin_gakuenImasCalculator/yellow.jpg
nonebot_plugin_gakuenImasCalculator/yellow.png
nonebot_plugin_gakuenImasCalculator/yellow2.jpg
nonebot_plugin_gakuenImasCalculator.egg-info/PKG-INFO
nonebot_plugin_gakuenImasCalculator.egg-info/SOURCES.txt
nonebot_plugin_gakuenImasCalculator.egg-info/dependency_links.txt
nonebot_plugin_gakuenImasCalculator.egg-info/requires.txt
nonebot_plugin_gakuenImasCalculator.egg-info/top_level.txt