Metadata-Version: 2.1
Name: nonebot-plugin-gakuenImasCalculator
Version: 0.1.2
Summary: NoneBot2学院偶像大师算分插件
Home-page: https://github.com/ikarosf/nonebot_plugin_gakuenImasCalculator
Author: ikarosf
Author-email: ikarosff@gmail.com
License: MIT Licence
Keywords: nonebot,plugin,gakuenImas,Calculator,gakuenIdolMaster
Platform: any
